spyder_remote_server/__init__.py
spyder_remote_server/api.py
spyder_remote_server/cli.py
spyder_remote_server/conda_api.py
spyder_remote_server/config.py
spyder_remote_server/constants.py
spyder_remote_server/daemon.py
spyder_remote_server/server.py
spyder_remote_server/utils.py
spyder_remote_server/scripts/conda-activate.bat
spyder_remote_server/scripts/conda-activate.sh
spyder_remote_server/templates/__init__.py
spyder_remote_server/templates/config.jinja2
spyder_remote_server-0.0.4.dist-info/LICENSE.txt
spyder_remote_server-0.0.4.dist-info/METADATA
spyder_remote_server-0.0.4.dist-info/WHEEL
spyder_remote_server-0.0.4.dist-info/entry_points.txt
spyder_remote_server-0.0.4.dist-info/top_level.txt
spyder_remote_server-0.0.4.dist-info/RECORD
