Metadata-Version: 2.1
Name: spyder-remote-server
Version: 0.0.4
Summary: Spyder remote server to connect to Spyder kernels via zeroconf.
Home-page: https://github.com/Semi-ATE/spyder-remote/tree/master/spyder-remote-server
License: UNKNOWN
Platform: UNKNOWN
Requires-Dist: click
Requires-Dist: daemoniker
Requires-Dist: jinja2
Requires-Dist: pyzmq
Requires-Dist: zeroconf (<=0.27)
